{
  "annotations": {
    "changelogDate": "20191222075352"
  },
  "applications": ["shop"],
  "entityTableName": "shipping_information",
  "fields": [
    {
      "fieldName": "deliveryAddress",
      "fieldType": "String"
    },
    {
      "fieldName": "shippingStatus",
      "fieldType": "String"
    }
  ],
  "jpaMetamodelFiltering": true,
  "name": "ShippingInformation",
  "relationships": [
    {
      "otherEntityName": "customer",
      "otherEntityRelationshipName": "shippingInformation",
      "relationshipName": "customer",
      "relationshipSide": "left",
      "relationshipType": "many-to-one"
    },
    {
      "otherEntityName": "order",
      "otherEntityRelationshipName": "shippingInformation",
      "relationshipName": "order",
      "relationshipSide": "right",
      "relationshipType": "one-to-one"
    }
  ],
  "searchEngine": "no",
  "service": "serviceClass"
}
